structure_derivation/__init__.py
structure_derivation/data/__init__.py
structure_derivation/helpers/__init__.py
structure_derivation/helpers/utils.py
structure_derivation/inference/__init__.py
structure_derivation/inference/batch_inference.py
structure_derivation/inference/inference.py
structure_derivation/model/__init__.py
structure_derivation/model/htsat.py
structure_derivation/model/layers.py
structure_derivation/model/model.py
structure_derivation/model/patch.py
structure_derivation/notebooks/__init__.py
structure_derivation/notebooks/data_creation.py
structure_derivation/train/__init__.py
structure_derivation/train/train.py
structure_derivation/train/training_config.py
structure_derivation-0.1.0.post1.dist-info/METADATA
structure_derivation-0.1.0.post1.dist-info/WHEEL
structure_derivation-0.1.0.post1.dist-info/top_level.txt
structure_derivation-0.1.0.post1.dist-info/RECORD
